kaleidoscope/__init__.py
kaleidoscope/metrics/__init__.py
kaleidoscope/metrics/_reference_values.py
kaleidoscope/metrics/collection.py
kaleidoscope/metrics/server.py
kaleidoscope/networks/__init__.py
kaleidoscope/networks/colour_net.py
kaleidoscope/networks/mutation.py
kaleidoscope/representations/__init__.py
kaleidoscope/representations/_reference_values.py
kaleidoscope/representations/_utilities.py
kaleidoscope/representations/conversions.py
kaleidoscope/representations/representations.py
torch_kaleidoscope-0.1.1.dist-info/licenses/LICENSE
torch_kaleidoscope-0.1.1.dist-info/METADATA
torch_kaleidoscope-0.1.1.dist-info/WHEEL
torch_kaleidoscope-0.1.1.dist-info/top_level.txt
torch_kaleidoscope-0.1.1.dist-info/RECORD
