Metadata-Version: 2.4
Name: torch-kaleidoscope
Version: 0.1.1
Summary: A tool kit for the use of non-RGB colour representations with torchvision and the PyTorch framework.
Author-email: Alexis J S Payne <academia@aksan.dev>
Keywords: machine learning,image processing,computer vision
Classifier: Development Status :: 2 - Pre-Alpha
Classifier: License :: OSI Approved :: BSD License
Classifier: Topic :: Scientific/Engineering :: Image Processing
Classifier: Topic :: Scientific/Engineering :: Artificial Intelligence
Classifier: Intended Audience :: Science/Research
Classifier: Programming Language :: Python :: 3
Requires-Python: >=3.8
License-File: LICENSE
Requires-Dist: torch>=2.6
Requires-Dist: torchvision>=0.21
Dynamic: license-file
